julius_cipher/__init__.py
julius_cipher/main.py
julius_cipher-4.1.0.dist-info/LICENSE
julius_cipher-4.1.0.dist-info/METADATA
julius_cipher-4.1.0.dist-info/WHEEL
julius_cipher-4.1.0.dist-info/entry_points.txt
julius_cipher-4.1.0.dist-info/top_level.txt
julius_cipher-4.1.0.dist-info/RECORD
