Metadata-Version: 2.2
Name: julius_cipher
Version: 4.1.0
Summary: A simple command line program use to encipher/decipher text to/from Caesar Cipher.
Home-page: https://github.com/uwungu01-rep/caesar-cipher-tool-python.edition
Author: Zizel
Author-email: danbua999@gmail.com
Classifier: Programming Language :: Python :: 3
Classifier: Operating System :: OS Independent
Classifier: License :: OSI Approved :: GNU General Public License v3 (GPLv3)
License-File: LICENSE
Requires-Dist: ziz_utils
Dynamic: author
Dynamic: author-email
Dynamic: classifier
Dynamic: description
Dynamic: description-content-type
Dynamic: home-page
Dynamic: requires-dist
Dynamic: summary
